.editorconfig
.gitignore
.gitlab-ci.yml
README.rst
publish.settings.sh
publish.sh
pyproject.toml
tsconfig.json
.idea/modules.xml
.idea/peek-plugin-graphdb.iml
.idea/inspectionProfiles/Project_Default.xml
.idea/inspectionProfiles/profiles_settings.xml
peek_plugin_graphdb/__init__.py
peek_plugin_graphdb/plugin_package.json
peek_plugin_graphdb.egg-info/PKG-INFO
peek_plugin_graphdb.egg-info/SOURCES.txt
peek_plugin_graphdb.egg-info/dependency_links.txt
peek_plugin_graphdb.egg-info/requires.txt
peek_plugin_graphdb.egg-info/top_level.txt
peek_plugin_graphdb/_private/PluginNames.py
peek_plugin_graphdb/_private/__init__.py
peek_plugin_graphdb/_private/alembic.ini
peek_plugin_graphdb/_private/admin-app/graphdb.module.ts
peek_plugin_graphdb/_private/admin-app/components/edit-setting-table/edit.component.html
peek_plugin_graphdb/_private/admin-app/components/edit-setting-table/edit.component.scss
peek_plugin_graphdb/_private/admin-app/components/edit-setting-table/edit.component.ts
peek_plugin_graphdb/_private/admin-app/components/graphdb-admin-page/graphdb-admin-page.component.html
peek_plugin_graphdb/_private/admin-app/components/graphdb-admin-page/graphdb-admin-page.component.scss
peek_plugin_graphdb/_private/admin-app/components/graphdb-admin-page/graphdb-admin-page.component.ts
peek_plugin_graphdb/_private/admin-app/components/status/status.component.html
peek_plugin_graphdb/_private/admin-app/components/status/status.component.scss
peek_plugin_graphdb/_private/admin-app/components/status/status.component.ts
peek_plugin_graphdb/_private/agent/AgentEntryHook.py
peek_plugin_graphdb/_private/agent/__init__.py
peek_plugin_graphdb/_private/alembic/__init__.py
peek_plugin_graphdb/_private/alembic/env.py
peek_plugin_graphdb/_private/alembic/script.py.mako
peek_plugin_graphdb/_private/alembic/versions/26f8d213ba06_tracerule_propname_nullable.py
peek_plugin_graphdb/_private/alembic/versions/4795161756fc_second_make_rule_prop_null.py
peek_plugin_graphdb/_private/alembic/versions/523b8e513a38_make_rule_prop_name_nullable.py
peek_plugin_graphdb/_private/alembic/versions/6dac32ecea20_added_trccfg_title.py
peek_plugin_graphdb/_private/alembic/versions/__init__.py
