Metadata-Version: 2.4
Name: peek-plugin-graphdb
Version: 5.0.4
Summary: Peek Plugin GraphDB - storage for a graph model with vertices and edges
Author-email: Synerty <contact@synerty.com>
Project-URL: Homepage, https://github.com/Synerty/peek-plugin-graphdb
Keywords: Peek,Python,Platform,synerty
Requires-Dist: peek-plugin-base==5.0.4
